pyobs_allsky_cloudcover-1.2.1.dist-info/METADATA
pyobs_allsky_cloudcover-1.2.1.dist-info/WHEEL
pyobs_cloudcover/world_model/wcs_model_loader.py
pyobs_cloudcover/world_model/hour_angle_converter.py
pyobs_cloudcover/world_model/__init__.py
pyobs_cloudcover/world_model/simple_model.py
pyobs_cloudcover/world_model/world_model_factory.py
pyobs_cloudcover/world_model/wcs_model.py
pyobs_cloudcover/world_model/world_model.py
pyobs_cloudcover/testing/__init__.py
pyobs_cloudcover/testing/module.py
pyobs_cloudcover/application.py
pyobs_cloudcover/cloud_info_calculator/coverage_info_calculator.py
pyobs_cloudcover/cloud_info_calculator/coverage_change_calculator.py
pyobs_cloudcover/cloud_info_calculator/cloud_info_calculator_factory.py
pyobs_cloudcover/cloud_info_calculator/__init__.py
pyobs_cloudcover/pipeline/pipeline_controller_factory.py
pyobs_cloudcover/pipeline/day/sun_masker.py
pyobs_cloudcover/pipeline/day/pipeline_factory.py
pyobs_cloudcover/pipeline/day/__init__.py
pyobs_cloudcover/pipeline/day/pipeline.py
pyobs_cloudcover/pipeline/day/pipeline_options.py
pyobs_cloudcover/pipeline/day/altaz_map_generator.py
pyobs_cloudcover/pipeline/day/color_ratio_calculation.py
pyobs_cloudcover/pipeline/day/debayer_image.py
pyobs_cloudcover/pipeline/night/preprocessor/preprocessor_factory.py
pyobs_cloudcover/pipeline/night/preprocessor/image_masker.py
pyobs_cloudcover/pipeline/night/preprocessor/image_binner.py
pyobs_cloudcover/pipeline/night/preprocessor/preprocessor.py
pyobs_cloudcover/pipeline/night/preprocessor/__init__.py
pyobs_cloudcover/pipeline/night/preprocessor/preprocessor_options.py
pyobs_cloudcover/pipeline/night/pipeline_factory.py
pyobs_cloudcover/pipeline/night/catalog/catalog_constructor_options.py
pyobs_cloudcover/pipeline/night/catalog/catalog_constructor_factory.py
pyobs_cloudcover/pipeline/night/catalog/catalog_constructor.py
pyobs_cloudcover/pipeline/night/catalog/__init__.py
pyobs_cloudcover/pipeline/night/catalog/altaz_catalog.py
pyobs_cloudcover/pipeline/night/catalog/altaz_catalog_loader.py
pyobs_cloudcover/pipeline/night/catalog/pixel_catalog.py
pyobs_allsky_cloudcover-1.2.1.dist-info/RECORD
