Metadata-Version: 2.3
Name: pyobs-allsky-cloudcover
Version: 1.2.1
Classifier: Programming Language :: Rust
Classifier: Programming Language :: Python :: Implementation :: CPython
Classifier: Programming Language :: Python :: Implementation :: PyPy
Requires-Dist: pyobs-core[full] >=1.13.4
Requires-Dist: influxdb-client >=1.42.0
Requires-Dist: opencv-python >=4.8.0.76
Requires-Dist: pytest >=7.4.0 ; extra == 'test'
Requires-Dist: pytest-cov >=4.1.0 ; extra == 'test'
Requires-Dist: pytest-mock >=3.11.1 ; extra == 'test'
Requires-Dist: pytest-asyncio >=0.21.1 ; extra == 'test'
Requires-Dist: pytest-aiohttp >=1.0.5 ; extra == 'test'
Requires-Dist: mypy >=1.9.0 ; extra == 'test'
Requires-Dist: testcontainers[influxdb] >=4.7.1 ; extra == 'test'
Requires-Dist: matplotlib ; extra == 'test'
Provides-Extra: test
Requires-Python: >=3.11
